qt_thread_updater/__init__.py
qt_thread_updater/__meta__.py
qt_thread_updater/global_utils.py
qt_thread_updater/thread_updater.py
qt_thread_updater/__pycache__/__init__.cpython-36.pyc
qt_thread_updater/__pycache__/__init__.cpython-38.pyc
qt_thread_updater/__pycache__/__meta__.cpython-36.pyc
qt_thread_updater/__pycache__/__meta__.cpython-38.pyc
qt_thread_updater/__pycache__/global_utils.cpython-36.pyc
qt_thread_updater/__pycache__/global_utils.cpython-38.pyc
qt_thread_updater/__pycache__/thread_updater.cpython-36.pyc
qt_thread_updater/__pycache__/thread_updater.cpython-38.pyc
qt_thread_updater/widgets/__init__.py
qt_thread_updater/widgets/quick_text_edit.py
qt_thread_updater/widgets/__pycache__/__init__.cpython-36.pyc
qt_thread_updater/widgets/__pycache__/__init__.cpython-38.pyc
qt_thread_updater/widgets/__pycache__/quick_text_edit.cpython-36.pyc
qt_thread_updater/widgets/__pycache__/quick_text_edit.cpython-38.pyc
qt_thread_updater-1.1.6.dist-info/LICENSE
qt_thread_updater-1.1.6.dist-info/METADATA
qt_thread_updater-1.1.6.dist-info/WHEEL
qt_thread_updater-1.1.6.dist-info/top_level.txt
qt_thread_updater-1.1.6.dist-info/RECORD
