Metadata-Version: 2.1
Name: qt-thread-updater
Version: 1.1.6
Summary: Python Qt thread updater to update GUI items using a separate thread.
Home-page: https://github.com/justengel/qt_thread_updater
Author: Justin Engel
Author-email: jtengel08@gmail.com
License: MIT
Download-URL: https://github.com/justengel/qt_thread_updater/archive/v1.1.6.tar.gz
Keywords: PyQt PyQt4 PyQt5 PySide PySide2 QtPy Thread Update GUI
Platform: any
Classifier: Programming Language :: Python
Classifier: Programming Language :: Python :: 3
Classifier: Operating System :: OS Independent
Requires-Dist: QtPy (>=1.9.0)
